MANIFEST.in
README.md
setup.cfg
setup.py
algocoin/.DS_Store
algocoin/__init__.py
algocoin/__main__.py
algocoin/backtest.py
algocoin/custom_strategies.py
algocoin/execution.py
algocoin/risk.py
algocoin/trading.py
algocoin.egg-info/PKG-INFO
algocoin.egg-info/SOURCES.txt
algocoin.egg-info/dependency_links.txt
algocoin.egg-info/entry_points.txt
algocoin.egg-info/not-zip-safe
algocoin.egg-info/top_level.txt
algocoin/lib/callback.py
algocoin/lib/config.py
algocoin/lib/data.py
algocoin/lib/data_source.py
algocoin/lib/define.py
algocoin/lib/enums.py
algocoin/lib/exceptions.py
algocoin/lib/exchange.py
algocoin/lib/logging.py
algocoin/lib/order_book.py
algocoin/lib/parser.py
algocoin/lib/strategy.py
algocoin/lib/structs.py
algocoin/lib/utils.py
algocoin/lib/exchanges/gdax.py
algocoin/lib/exchanges/gemini.py
algocoin/lib/exchanges/helpers.py
algocoin/lib/exchanges/itbit.py
algocoin/lib/exchanges/kraken.py
algocoin/lib/oe/gemini.py
algocoin/lib/oe/itbit_api.py
algocoin/lib/oe/poloniex/__init__.py
algocoin/lib/oe/poloniex/coach.py
algocoin/lib/strategies/sma_crosses_strategy.py
algocoin/lib/strategies/sma_crosses_strategy_with_regression_follow.py
algocoin/lib/strategies/test_strat.py
algocoin/tests/__init__.py
algocoin/tests/test_all.py
algocoin/tests/test_backtest.py
algocoin/tests/test_callback.py
algocoin/tests/test_config.py
algocoin/tests/test_custom_strategies.py
algocoin/tests/test_data.py
algocoin/tests/test_data_source.py
algocoin/tests/test_define.py
algocoin/tests/test_enums.py
algocoin/tests/test_exchange.py
algocoin/tests/test_execution.py
algocoin/tests/test_main.py
algocoin/tests/test_risk.py
algocoin/tests/test_strategy.py
algocoin/tests/test_structs.py
algocoin/tests/test_trading.py
algocoin/tests/test_utils.py
algocoin/tests/exchanges/__init__.py
algocoin/tests/exchanges/test_gdax.py
algocoin/tests/exchanges/test_gemini.py
algocoin/tests/strategies/__init__.py
algocoin/tests/strategies/test_sma_crosses_strategy.py
algocoin/ui/__init__.py
algocoin/ui/server.py