Metadata-Version: 1.1
Name: algocoin
Version: 0.0.2
Summary: Algorithmic trading library for cryptocurrencies
Home-page: https://github.com/timkpaine/algo-coin
Author: Tim Paine
Author-email: timothy.k.paine@gmail.com
License: GPL
Download-URL: https://github.com/timkpaine/algo-coin/archive/v0.0.2.tar.gz
Keywords: algorithmic trading cryptocurrencies
Platform: UNKNOWN
Classifier: Development Status :: 3 - Alpha
Classifier: Programming Language :: Python :: 2
Classifier: Programming Language :: Python :: 2.7
Classifier: Programming Language :: Python :: 3
Classifier: Programming Language :: Python :: 3.3
Classifier: Programming Language :: Python :: 3.4
Classifier: Programming Language :: Python :: 3.5
